fivetran_custom_sdk/__init__.py
fivetran_custom_sdk/__main__.py
fivetran_custom_sdk/protos/__init__.py
fivetran_custom_sdk/protos/common_pb2.py
fivetran_custom_sdk/protos/common_pb2.pyi
fivetran_custom_sdk/protos/common_pb2_grpc.py
fivetran_custom_sdk/protos/connector_sdk_pb2.py
fivetran_custom_sdk/protos/connector_sdk_pb2.pyi
fivetran_custom_sdk/protos/connector_sdk_pb2_grpc.py
fivetran_custom_sdk/protos/destination_sdk_pb2.py
fivetran_custom_sdk/protos/destination_sdk_pb2.pyi
fivetran_custom_sdk/protos/destination_sdk_pb2_grpc.py
fivetran_custom_sdk-0.1.19.4.dist-info/LICENSE
fivetran_custom_sdk-0.1.19.4.dist-info/METADATA
fivetran_custom_sdk-0.1.19.4.dist-info/WHEEL
fivetran_custom_sdk-0.1.19.4.dist-info/top_level.txt
fivetran_custom_sdk-0.1.19.4.dist-info/RECORD
