Metadata-Version: 2.1
Name: fivetran_custom_sdk
Version: 0.1.19.4
Summary: Build custom connectors as an extension of Fivetran
Author-email: Fivetran <developers@fivetran.com>
Project-URL: Homepage, https://github.com/fivetran/fivetran_custom_sdk
Project-URL: Issues, https://github.com/fivetran/fivetran_custom_sdk/issues
Classifier: Programming Language :: Python :: 3
Classifier: License :: OSI Approved :: MIT License
Classifier: Operating System :: OS Independent
Requires-Python: >=3.8
License-File: LICENSE
Requires-Dist: grpcio ==1.59.3
Requires-Dist: grpcio-tools ==1.59.3
Requires-Dist: docker ==6.1.3
